{
  "id": "3614689",
  "name": "klassno",
  "font_family": "knofont",
  "css_prefix_text": "kno",
  "description": "klassno",
  "glyphs": [
    {
      "icon_id": "109728",
      "name": "delete",
      "font_class": "delete",
      "unicode": "e60f",
      "unicode_decimal": 58895
    },
    {
      "icon_id": "22891849",
      "name": "star",
      "font_class": "star",
      "unicode": "e65e",
      "unicode_decimal": 58974
    },
    {
      "icon_id": "88609",
      "name": "copy",
      "font_class": "copy",
      "unicode": "e706",
      "unicode_decimal": 59142
    },
    {
      "icon_id": "22273061",
      "name": "poker-spade",
      "font_class": "poker-spade",
      "unicode": "e679",
      "unicode_decimal": 59001
    },
    {
      "icon_id": "15838434",
      "name": "back",
      "font_class": "back",
      "unicode": "e666",
      "unicode_decimal": 58982
    },
    {
      "icon_id": "12932078",
      "name": "l-menu",
      "font_class": "menu",
      "unicode": "e795",
      "unicode_decimal": 59285
    }
  ]
}
